picklenote/__init__.py
picklenote/pickler.py
picklenote-0.0.1.dist-info/LICENSE
picklenote-0.0.1.dist-info/METADATA
picklenote-0.0.1.dist-info/WHEEL
picklenote-0.0.1.dist-info/top_level.txt
picklenote-0.0.1.dist-info/RECORD
