Metadata-Version: 2.1
Name: picklenote
Version: 0.0.1
Summary: Pickle an object together with a short note about it
Home-page: https://github.com/kentwait/picklenote
Author: Kent Kawashima
Author-email: kentkawashima@gmail.com
License: UNKNOWN
Platform: UNKNOWN
Classifier: Programming Language :: Python :: 3
Classifier: License :: OSI Approved :: MIT License
Classifier: Operating System :: OS Independent
Classifier: Topic :: Utilities
Requires-Python: >=3.6
